{
    "root": [
    {
        "name": 'Alex',
        "age": 29
    },
    {
        "name": 'Alex Two',
        "age": 29
    },
    {
        "name": 'Alex Three',
        "age": 29
    },
    {
        "name": 'Alex Four',
        "age": 29
    },
    {
        "name": 'Alex Five',
        "age": 29
    },
    {
        "name": 'Alex Six',
        "age": 29
    },
    {
        "name": 'Alex 1',
        "age": 29
    },
    {
        "name": 'Alex 2',
        "age": 34
    },
    {
        "name": 'Alex 6',
        "age": 43
    },
    {
        "name": 'Alex 7',
        "age": 3
    },
    {
        "name": 'Alex 2',
        "age": 45
    },
    {
        "name": 'Alex 9',
        "age": 7
    },
    {
        "name": 'Alex 12',
        "age": 11
    },
    {
        "name": 'Alex Two',
        "age": 22
    },
    {
        "name": 'Alex Two',
        "age": 44
    }
    ]
}
